mldice/__init__.py
mldice/featurization.py
mldice/main.py
mldice/predict.py
mldice/predicting.py
mldice/utils.py
mldice/validation.py
mldice/models/DNN/featureSpace.csv
mldice/models/DNN/IM_impurity/DNN_model
mldice/models/DNN/IM_self/DNN_model
mldice/models/DNN/MCA_chemical/DNN_model
mldice/models/DNN/MCA_impurity/DNN_model
mldice/models/DNN/MCA_self/DNN_model
mldice/models/RF/featureSpace.csv
mldice/models/RF/IM_impurity/RF_model
mldice/models/RF/IM_self/RF_model
mldice/models/RF/MCA_chemical/RF_model
mldice-0.2.0.data/data/mldice/DNN_model
mldice-0.2.0.data/data/mldice/RF_model
mldice-0.2.0.data/data/mldice/featureSpace.csv
mldice-0.2.0.dist-info/METADATA
mldice-0.2.0.dist-info/WHEEL
mldice-0.2.0.dist-info/entry_points.txt
mldice-0.2.0.dist-info/top_level.txt
mldice-0.2.0.dist-info/RECORD
