Metadata-Version: 2.1
Name: mldice
Version: 0.2.0
Summary: Machine Learned Diffusion Coefficient Estimator - ML-DiCE is an ML framework that can predict five modes of elemental diffusion in alloys 
Home-page: https://github.com/yanqingsu/ML-DiCE
Author: Arjun S Kulathuvayal
Author-email: skvarjun@gmail.com
License: MIT
Platform: UNKNOWN
Requires-Python: >=3
Requires-Dist: numpy ==1.24.4
Requires-Dist: scikit-learn ==1.3.0
Requires-Dist: mendeleev
Requires-Dist: seaborn
